create_api_app/conf/__init__.py
create_api_app/conf/constants/__init__.py
create_api_app/conf/constants/content.py
create_api_app/conf/constants/filepaths.py
create_api_app/conf/file_handler.py
create_api_app/conf/storage.py
create_api_app/main.py
create_api_app/setup/__init__.py
create_api_app/setup/backend.py
create_api_app/setup/base.py
create_api_app/setup/clean.py
create_api_app/setup/frontend.py
create_api_app/setup_assets/backend/app/__init__.py
create_api_app/setup_assets/backend/app/config/__init__.py
create_api_app/setup_assets/backend/app/config/settings.py
create_api_app/setup_assets/backend/app/db/__init__.py
create_api_app/setup_assets/backend/app/enums/__init__.py
create_api_app/setup_assets/backend/app/main.py
create_api_app/setup_assets/backend/app/models/__init__.py
create_api_app/setup_assets/backend/app/routers/__init__.py
create_api_app/setup_assets/backend/app/start.py
create_api_app/setup_assets/backend/app/utils/__init__.py
create_api_app/setup_assets/backend/app/utils/fileloader.py
create_api_app/setup_assets/backend/README.md
create_api_app/setup_assets/backend/tests/__init__.py
create_api_app/setup_assets/frontend/next.config.mjs
create_api_app/setup_assets/frontend/src/app/globals.css
create_api_app/setup_assets/frontend/src/app/layout.tsx
create_api_app/setup_assets/frontend/src/app/page.tsx
create_api_app/setup_assets/frontend/src/hooks/useFetchData.tsx
create_api_app/setup_assets/frontend/src/lib/queries.ts
create_api_app/setup_assets/frontend/src/lib/utils.ts
create_api_app/setup_assets/frontend/src/pages/Homepage/Homepage.tsx
create_api_app/setup_assets/frontend/src/pages/Homepage/index.tsx
create_api_app/setup_assets/root/.env.local
create_api_app/setup_assets/root/.gitignore
create_api_app/setup_assets/root/README.md
create_api_app/setup_assets/uploadthing/src/app/api/uploadthing/list-files/route.ts
create_api_app/setup_assets/uploadthing/src/hooks/useFetchImgs.tsx
create_api_app/setup_assets/uploadthing/src/lib/constants.ts
create_api_app-2.1.2.dist-info/entry_points.txt
create_api_app-2.1.2.dist-info/LICENSE
create_api_app-2.1.2.dist-info/METADATA
create_api_app-2.1.2.dist-info/WHEEL
create_api_app-2.1.2.dist-info/RECORD
