Metadata-Version: 2.1
Name: create-api-app
Version: 2.1.2
Summary: A quickstart tool for creating a FastAPI project with a NextJS frontend.
Author: Ryan Partridge
Author-email: rpartridge101@gmail.com
Requires-Python: >=3.12,<4.0
Classifier: Programming Language :: Python :: 3
Classifier: Programming Language :: Python :: 3.12
Requires-Dist: build_nextjs_app (>=1.0.2,<2.0.0)
Requires-Dist: docker (>=7.1.0,<8.0.0)
Requires-Dist: typer[all] (>=0.12.3,<0.13.0)
